camino/__init__.py
camino/__main__.py
camino/data.py
camino/problem.py
camino/runner.py
camino/settings.py
camino/solver.py
camino/stats.py
camino/problems/__init__.py
camino/problems/double_tank.py
camino/problems/dsc.py
camino/problems/load_problem_from_nl_file.py
camino/problems/manual_formulation_from_minlplib.py
camino/problems/problem_collection.py
camino/problems/sto_based.py
camino/problems/time_opt.py
camino/problems/gearbox/__init__.py
camino/problems/gearbox/models.py
camino/problems/solarsys/__init__.py
camino/problems/solarsys/ambient.py
camino/problems/solarsys/simulator.py
camino/problems/solarsys/system.py
camino/solvers/__init__.py
camino/solvers/utils.py
camino/solvers/approximation/__init__.py
camino/solvers/approximation/cia.py
camino/solvers/approximation/sur.py
camino/solvers/decomposition/__init__.py
camino/solvers/decomposition/base.py
camino/solvers/decomposition/benders_master.py
camino/solvers/decomposition/oa_master.py
camino/solvers/decomposition/sequential_benders_master.py
camino/solvers/decomposition/voronoi_master.py
camino/solvers/external/__init__.py
camino/solvers/external/ampl.py
camino/solvers/external/bonmin.py
camino/solvers/mip/__init__.py
camino/solvers/pumps/__init__.py
camino/solvers/pumps/base.py
camino/solvers/pumps/base_random.py
camino/solvers/pumps/projection_random.py
camino/solvers/pumps/projections.py
camino/solvers/pumps/utils.py
camino/solvers/relaxation/__init__.py
camino/solvers/sequential/__init__.py
camino/solvers/sequential/milp_tr.py
camino/solvers/subsolvers/__init__.py
camino/solvers/subsolvers/fnlp.py
camino/solvers/subsolvers/fnlp_closest.py
camino/solvers/subsolvers/nlp.py
camino/utils/__init__.py
camino/utils/cache.py
camino/utils/conversion.py
camino/utils/data.py
camino/utils/debugtools.py
camino/utils/integrators.py
camino/utils/plot.py
camino/utils/validate.py
caminopy-0.1.4.dist-info/licenses/LICENSE
caminopy-0.1.4.dist-info/METADATA
caminopy-0.1.4.dist-info/WHEEL
caminopy-0.1.4.dist-info/top_level.txt
caminopy-0.1.4.dist-info/RECORD
